setup.py
src/memorycoin_python.egg-info/PKG-INFO
src/memorycoin_python.egg-info/SOURCES.txt
src/memorycoin_python.egg-info/dependency_links.txt
src/memorycoin_python.egg-info/top_level.txt
src/memorycoinrpc/__init__.py
src/memorycoinrpc/config.py
src/memorycoinrpc/connection.py
src/memorycoinrpc/data.py
src/memorycoinrpc/exceptions.py
src/memorycoinrpc/proxy.py
src/memorycoinrpc/util.py