Metadata-Version: 1.1
Name: memorycoin-python
Version: 0.1
Summary: Friendly Memorycoin JSON-RPC API binding for Python
Home-page: http://github.com/emre
Author: Emre Yilmaz
Author-email: mail@emreyilmaz.me
License: UNKNOWN
Platform: UNKNOWN
Classifier: Development Status :: 4 - Beta
Classifier: Environment :: Console
Classifier: Environment :: Web Environment
Classifier: Intended Audience :: Developers
Classifier: Programming Language :: Python
Classifier: License :: OSI Approved :: MIT License
Classifier: Topic :: Office/Business :: Financial
